LICENSE
MANIFEST.in
NOTICE
README.md
setup.cfg
setup.py
versioneer.py
bin/anc-policy
bin/create-new-pxgrid-account
bin/endpoint-query-all
bin/matrix-query-all
bin/profiles-query-all
bin/px-publish
bin/px-subscribe
bin/session-query-all
bin/session-query-by-ip
bin/sgacls-query-all
bin/sgts-query-all
bin/sxp-query-bindings
bin/system-query-all
bin/user-groups-query
pxgrid_util/__init__.py
pxgrid_util/_version.py
pxgrid_util/config.py
pxgrid_util/create_account_config.py
pxgrid_util/pxgrid.py
pxgrid_util/stomp.py
pxgrid_util/ws_stomp.py
pxgrid_util.egg-info/PKG-INFO
pxgrid_util.egg-info/SOURCES.txt
pxgrid_util.egg-info/dependency_links.txt
pxgrid_util.egg-info/requires.txt
pxgrid_util.egg-info/top_level.txt